gnome_shell_install_extension/__init__.py
gnome_shell_install_extension/main.py
gnome_shell_install_extension-1.1.0.dist-info/LICENSE
gnome_shell_install_extension-1.1.0.dist-info/METADATA
gnome_shell_install_extension-1.1.0.dist-info/WHEEL
gnome_shell_install_extension-1.1.0.dist-info/entry_points.txt
gnome_shell_install_extension-1.1.0.dist-info/top_level.txt
gnome_shell_install_extension-1.1.0.dist-info/RECORD
