Metadata-Version: 2.1
Name: gnome-shell-install-extension
Version: 1.1.0
Summary: Install Gnome Shell extension from zip files.
Home-page: https://github.com/zakora/gnome-shell-install-extension
Author: zakora
License: UNKNOWN
Platform: UNKNOWN
Classifier: Development Status :: 5 - Production/Stable
Classifier: Environment :: X11 Applications :: Gnome
Classifier: Intended Audience :: End Users/Desktop
Classifier: License :: OSI Approved :: Apache Software License
Classifier: Operating System :: POSIX :: Linux
Classifier: Programming Language :: Python :: 3
Classifier: Programming Language :: Python :: 3.5
Classifier: Programming Language :: Python :: 3.6
Classifier: Programming Language :: Python :: 3.7
Classifier: Topic :: Desktop Environment :: Gnome
Requires-Python: ~=3.5
